{
  "id": "book_015",
  "title": "拔萝卜",
  "coverPath": "",
  "mode": "textOnly",
  "estimatedMinutes": 7,
  "pages": [
    {
      "id": "p1",
      "segments": [
        { "id": "s1", "text": "从前，在一个小村庄里，住着一位白胡子的老爷爷。老爷爷特别爱种菜，他有一块小小的菜地，每天都在地里忙活。" },
        { "id": "s2", "text": "春天，老爷爷在地里撒下一粒萝卜种子。他每天浇水、施肥、除草，盼着萝卜快快长大。" },
        { "id": "s3", "text": "太阳暖暖地照着，雨水甜甜地浇着，萝卜一天一天地长大。叶子绿油油的，又大又嫩。" },
        { "id": "s4", "text": "终于，秋天到了，该收萝卜啦！老爷爷来到地里，抓住萝卜叶子，弯下腰，用力一拔——" },
        { "id": "s5", "text": "“嗨哟！嗨哟！”可是，萝卜一动也不动。原来啊，这个萝卜长得太大了，大得像个小水桶，老爷爷一个人根本拔不动。" }
      ]
    },
    {
      "id": "p2",
      "segments": [
        { "id": "s6", "text": "老爷爷擦擦汗，喊道：“老婆婆，老婆婆！快来帮我拔萝卜呀！”" },
        { "id": "s7", "text": "老婆婆听见喊声，连忙放下手里的活儿，从屋里跑了出来：“来啦来啦！老公公，我帮你一起拔！”" },
        { "id": "s8", "text": "老婆婆拉住老爷爷的手，老爷爷抓住萝卜叶子，两个人一起使劲——“嗨哟！嗨哟！拔萝卜！”" },
        { "id": "s9", "text": "可是，萝卜还是一动不动。这个萝卜真是太大了，两个人也拔不动。" }
      ]
    },
    {
      "id": "p3",
      "segments": [
        { "id": "s10", "text": "老爷爷和老奶奶面面相觑，怎么办呢？老奶奶想了个主意：“咱们叫小孙女来帮忙吧！”" },
        { "id": "s11", "text": "“小孙女，小孙女！快来帮我们拔萝卜呀！”老奶奶扯着嗓子喊。" },
        { "id": "s12", "text": "小孙女正在屋里玩布娃娃，听见奶奶喊，连忙跑了出来：“来啦来啦！爷爷奶奶，我帮你们一起拔！”" },
        { "id": "s13", "text": "小孙女拉住老奶奶的衣服，老奶奶拉住老爷爷的手，老爷爷抓住萝卜叶子，三个人一起使劲——“嗨哟！嗨哟！拔萝卜！”" },
        { "id": "s14", "text": "可是，萝卜还是一动不动。这个萝卜实在是太大了，三个人也拔不动呀！" }
      ]
    },
    {
      "id": "p4",
      "segments": [
        { "id": "s15", "text": "小孙女眨眨眼睛，说：“奶奶，咱们叫小花狗来帮忙吧！小花狗力气可大啦！”" },
        { "id": "s16", "text": "“小花狗，小花狗！快来帮我们拔萝卜呀！”大家一起喊。" },
        { "id": "s17", "text": "小花狗正在院子里啃骨头，听见喊声，汪汪汪地跑过来：“汪汪！来啦来啦！我也来帮忙！”" },
        { "id": "s18", "text": "小花狗咬住小孙女的裙子，小孙女拉住老奶奶的衣服，老奶奶拉住老爷爷的手，老爷爷抓住萝卜叶子。" },
        { "id": "s19", "text": "四个人（还有一只狗）一起使劲——“嗨哟！嗨哟！拔萝卜！”" },
        { "id": "s20", "text": "可是，萝卜还是一动不动。这个萝卜真的、真的太大了！" }
      ]
    },
    {
      "id": "p5",
      "segments": [
        { "id": "s21", "text": "小花狗摇摇尾巴，说：“汪汪！叫小猫来帮忙吧！小猫虽然小，可多一个人就多一份力气呀！”" },
        { "id": "s22", "text": "“小花猫，小花猫！快来帮我们拔萝卜呀！”大家一起喊。" },
        { "id": "s23", "text": "小花猫正在墙根下晒太阳，听见喊声，喵喵喵地跑过来：“喵喵！来啦来啦！我也来帮忙！”" },
        { "id": "s24", "text": "小花猫拉住小花狗的尾巴，小花狗咬住小孙女的裙子，小孙女拉住老奶奶的衣服，老奶奶拉住老爷爷的手，老爷爷抓住萝卜叶子。" },
        { "id": "s25", "text": "五个人（还有一只狗一只猫）一起使劲——“嗨哟！嗨哟！拔萝卜！”" },
        { "id": "s26", "text": "可是，萝卜还是一动不动。这萝卜简直像长在了地里一样！" }
      ]
    },
    {
      "id": "p6",
      "segments": [
        { "id": "s27", "text": "这时候，一只小老鼠从洞里探出头来，吱吱叫着：“吱吱！我也能帮忙吗？我虽然小，可多一个就多一份力气呀！”" },
        { "id": "s28", "text": "大家都笑了：“好呀好呀，小老鼠，你也来帮忙！”" },
        { "id": "s29", "text": "小老鼠拉住小花猫的尾巴，小花猫拉住小花狗的尾巴，小花狗咬住小孙女的裙子，小孙女拉住老奶奶的衣服，老奶奶拉住老爷爷的手，老爷爷抓住萝卜叶子。" },
        { "id": "s30", "text": "六个人（还有一只狗一只猫一只老鼠）一起使劲——“嗨哟！嗨哟！拔萝卜！用力拔呀用力拔！”" }
      ]
    },
    {
      "id": "p7",
      "segments": [
        { "id": "s31", "text": "只听“啵——”的一声，大萝卜终于被拔出来啦！" },
        { "id": "s32", "text": "哎呀，好大好大的一个萝卜呀！红红的皮，圆圆的身子，绿绿的叶子，比小孙女还要高，比小花狗还要重！" },
        { "id": "s33", "text": "大家一屁股坐在地上，你看看我，我看看你，都哈哈大笑起来。“拔出来啦！拔出来啦！”" },
        { "id": "s34", "text": "老爷爷摸摸胡子，乐呵呵地说：“哎呀，多亏了大家伙儿帮忙呀！一个人拔不动，两个人拔不动，可大家伙儿齐心协力，就把它拔出来啦！”" },
        { "id": "s35", "text": "小孙女抱着小老鼠说：“小老鼠，谢谢你！别看你小，没有你最后那一拉，咱们还拔不出来呢！”" },
        { "id": "s36", "text": "小老鼠得意地吱吱叫：“吱吱！你看，我也有用吧！”大家都笑了。" }
      ]
    },
    {
      "id": "p8",
      "segments": [
        { "id": "s37", "text": "晚上，老奶奶用这个大萝卜做了一锅香喷喷的萝卜汤，还做了萝卜饼、萝卜糕。大家围坐在一起，吃得可香啦！" },
        { "id": "s38", "text": "小花狗啃萝卜骨头，小花猫舔萝卜汤，小老鼠吱吱吱地吃萝卜丁，每个人都吃得很饱很饱。" },
        { "id": "s39", "text": "老爷爷笑着说：“你看，大家一起干活，再大的萝卜也能拔出来；大家一起吃饭，再普通的萝卜也变得特别香！" },
        { "id": "s40", "text": "这就是团结的力量呀！”" },
        { "id": "s41", "text": "这个故事告诉我们：一个人的力量是有限的，可是大家团结起来，齐心协力，就能做成很难很难的事情。" },
        { "id": "s42", "text": "不管力气大小，每个人都能尽一份力；多一个人，就多一份力量。团结起来，力量大，这就是“拔萝卜”的智慧呀。" }
      ]
    }
  ]
}
