{
  "id": "book_008",
  "title": "丑小鸭",
  "coverPath": "",
  "mode": "textOnly",
  "estimatedMinutes": 10,
  "pages": [
    {
      "id": "p1",
      "segments": [
        {
          "id": "s1",
          "text": "夏天到了，乡下的风景美极了。金黄的麦田在风里摇晃，绿油油的草地一直铺到小河边。"
        },
        {
          "id": "s2",
          "text": "在一片幽静的草地上，鸭妈妈正在窝里孵蛋。她已经坐了好些日子了，盼着小宝贝们快点出来。"
        },
        {
          "id": "s3",
          "text": "“咔嚓、咔嚓”——蛋壳一个接一个地破了，毛茸茸的小鸭子一个个探出了黄澄澄的小脑袋，唧唧唧地叫着妈妈。"
        },
        {
          "id": "s4",
          "text": "鸭妈妈高兴地数着：“一个、两个、三个、四个……咦？还有最大的一个蛋怎么还没破？”她又耐心地等了几天。"
        },
        {
          "id": "s5",
          "text": "终于，最大的蛋“咔嚓”一声裂开了，从里面钻出来一只又大又灰的小家伙，跟其他小鸭子一点儿也不像。"
        },
        {
          "id": "s6",
          "text": "鸭妈妈仔细看了看，嘀咕道：“这只小鸭子怎么这么大、这么灰？该不会是一只小火鸡吧？不过，他毕竟是我亲生的孩子呀。”"
        }
      ]
    },
    {
      "id": "p2",
      "segments": [
        {
          "id": "s7",
          "text": "第二天，鸭妈妈带着孩子们去河边散步。她想让邻居们看看她的宝贝们。"
        },
        {
          "id": "s8",
          "text": "其他鸭子看见这只又大又灰的小家伙，纷纷嘲笑起来：“瞧瞧，那个丑八怪是从哪儿来的？真是给我们鸭子家族丢脸！”"
        },
        {
          "id": "s9",
          "text": "一只鸭子冲过来啄他，一只小鸡也来欺负他，连火鸡都伸长脖子啄他的脖子。可怜的小家伙只是默默地承受着，一点儿也不明白为什么大家都不喜欢他。"
        },
        {
          "id": "s10",
          "text": "鸭妈妈也护不住他，只好叹了口气：“孩子呀，你别怪妈妈，要怪就怪你长得跟别人不一样。”"
        },
        {
          "id": "s11",
          "text": "从此，大家都叫他“丑小鸭”。丑小鸭每天都被欺负，兄弟姐妹也来啄他，他难过极了，眼泪吧嗒吧嗒地掉。"
        }
      ]
    },
    {
      "id": "p3",
      "segments": [
        {
          "id": "s12",
          "text": "一天夜里，丑小鸭趁着大家睡觉，偷偷地溜出了鸭棚。他一个人走过田野，走过沼泽，走啊走啊，累得实在走不动了。"
        },
        {
          "id": "s13",
          "text": "他来到一片野鸭住的沼泽地，躺在芦苇丛里过了一夜。第二天，野鸭们看见他，都好奇地围过来：“你是什么鸟呀？长得可真丑！”"
        },
        {
          "id": "s14",
          "text": "丑小鸭低着头，不说话。野鸭们还算好心，没有赶他走，但也没有谁能跟他做朋友。"
        },
        {
          "id": "s15",
          "text": "过了几天，两只大雁飞过来，看见了丑小鸭，哈哈大笑：“喂，丑家伙，要不要跟我们一起飞到天上去呀？”"
        },
        {
          "id": "s16",
          "text": "丑小鸭还没来得及回答，突然“砰——砰——”两声枪响，两只大雁应声栽进了芦苇丛。原来，猎人正在打猎！"
        }
      ]
    },
    {
      "id": "p4",
      "segments": [
        {
          "id": "s17",
          "text": "枪声四起，猎狗在芦苇丛里乱窜，水花四溅。丑小鸭吓得魂飞魄散，缩成一团，连大气都不敢出。"
        },
        {
          "id": "s18",
          "text": "一只大猎狗跑到他跟前，闻了闻他，又跑开了。“汪汪！”丑小鸭心想：“猎狗都不肯咬我，一定是因为我太丑了，连狗都嫌弃我。”"
        },
        {
          "id": "s19",
          "text": "天黑了，猎人们都走了，丑小鸭才敢出来。他拼命地跑啊跑啊，跑过田野，跑过小山，最后跑到了一座小破屋前。"
        },
        {
          "id": "s20",
          "text": "屋里住着一位老太太、一只猫和一只母鸡。老太太眼神不好，以为丑小鸭是一只肥鸭，就收留了他，希望他下蛋。"
        },
        {
          "id": "s21",
          "text": "可是丑小鸭是只公鸭子，怎么会下蛋呢？猫和母鸡都嘲笑他：“你不会咪咪叫，也不会下蛋，你到底有什么用？”"
        }
      ]
    },
    {
      "id": "p5",
      "segments": [
        {
          "id": "s22",
          "text": "丑小鸭委屈地说：“我想到外面的世界去看看，想到水里去游泳。”猫和母鸡都笑他傻，他只好悄悄地离开了小破屋。"
        },
        {
          "id": "s23",
          "text": "秋天到了，树叶变得金黄，纷纷落下。一天傍晚，丑小鸭正在湖边游水，忽然看见一群美丽的大鸟从远处飞来。"
        },
        {
          "id": "s24",
          "text": "那些大鸟浑身雪白，脖子又长又柔软，翅膀宽大有力——啊，那是美丽的天鹅！他们发出了奇异的叫声，展翅飞向远方。"
        },
        {
          "id": "s25",
          "text": "丑小鸭望着他们，心里有一种说不出的激动。他伸长脖子，也学着天鹅叫了起来，眼睛里涌出了泪水。"
        },
        {
          "id": "s26",
          "text": "“我虽然丑，可我也想和那些美丽的大鸟在一起……”他望着天鹅远去的身影，久久不愿离去。"
        }
      ]
    },
    {
      "id": "p6",
      "segments": [
        {
          "id": "s27",
          "text": "冬天来了，天气越来越冷。湖面开始结冰，丑小鸭的脚被冻在了冰里，动弹不得，冷得直发抖。"
        },
        {
          "id": "s28",
          "text": "幸好，第二天早晨一位农夫路过，用木鞋敲碎了冰，把丑小鸭救回了家，交给了妻子。"
        },
        {
          "id": "s29",
          "text": "农夫的孩子们想跟丑小鸭玩，可他以为孩子们要欺负他，吓得在屋子里乱飞，打翻了牛奶，弄乱了面粉，被农夫的妻子赶了出去。"
        },
        {
          "id": "s30",
          "text": "整个冬天，丑小鸭躲在芦苇丛里，挨饿受冻，受尽了苦难。寒风刺骨，大雪纷飞，他蜷缩成一团，咬着牙，一天一天地熬着。"
        },
        {
          "id": "s31",
          "text": "他常常想起那些美丽的天鹅，心里默默地念叨：“只要能熬过这个冬天，我一定要去找到他们……”"
        }
      ]
    },
    {
      "id": "p7",
      "segments": [
        {
          "id": "s32",
          "text": "终于，春天来了。阳光暖洋洋地照着大地，百灵鸟唱起了歌，草地变绿了，桃花开了。丑小鸭伸展了一下翅膀，发现翅膀变得很有力。"
        },
        {
          "id": "s33",
          "text": "他用力一拍翅膀，竟然飞了起来！他越飞越高，越飞越远，一直飞到了一座大花园里。"
        },
        {
          "id": "s34",
          "text": "花园里，三只美丽的天鹅正在湖面上游来游去，他们的羽毛洁白如雪，姿态优雅极了。"
        },
        {
          "id": "s35",
          "text": "丑小鸭看着他们，心里既激动又害怕：“我要去找他们，他们也许会因为我丑而啄死我，可是我宁可被他们啄死，也要和他们在一起！”"
        }
      ]
    },
    {
      "id": "p8",
      "segments": [
        {
          "id": "s36",
          "text": "丑小鸭鼓起勇气，飞到湖面上，向三只天鹅游去。天鹅们看见他，也拍着翅膀向他游过来。"
        },
        {
          "id": "s37",
          "text": "“杀死我吧！”丑小鸭低下头，等着被啄。可就在这时，他看见了清澈湖水中自己的倒影。"
        },
        {
          "id": "s38",
          "text": "倒影里不是一只又大又丑的灰鸭子，而是一只雪白美丽的天鹅！长长的脖子，洁白的羽毛，优雅的身姿——他不再是丑小鸭，他已经变成了一只美丽的天鹅！"
        },
        {
          "id": "s39",
          "text": "“这是我吗？这真的是我吗？”丑小鸭简直不敢相信自己的眼睛，他在水里转了一圈又一圈，那美丽的天鹅也跟着他转了一圈又一圈。"
        },
        {
          "id": "s40",
          "text": "原来，丑小鸭本不是鸭子，他是从天鹅蛋里孵出来的天鹅！他小时候之所以又大又灰，只是因为他是一只小天鹅呀。"
        }
      ]
    },
    {
      "id": "p9",
      "segments": [
        {
          "id": "s41",
          "text": "花园里来了一群孩子，他们往湖里扔面包屑，高兴地喊：“看啊，又来了一只新的天鹅！他是最年轻、最美丽的一只！”"
        },
        {
          "id": "s42",
          "text": "其他老天鹅也游过来，用嘴亲切地抚摸他的羽毛，表示欢迎。丑小鸭又害羞又幸福，把头藏进了翅膀里。"
        },
        {
          "id": "s43",
          "text": "他心里有说不出的快乐，可一点也不骄傲。他想起了从前受过的苦，想起了那些嘲笑和欺负，心里反而充满了感激。"
        },
        {
          "id": "s44",
          "text": "“一颗好心是不会骄傲的。”他轻声对自己说，“我经历了那么多磨难，所以更懂得珍惜今天的幸福。”"
        }
      ]
    },
    {
      "id": "p10",
      "segments": [
        {
          "id": "s45",
          "text": "从此，丑小鸭成了一只幸福的天鹅，他和其他天鹅一起在湖上快乐地生活。"
        },
        {
          "id": "s46",
          "text": "他常常对着夕阳，回忆起那些艰难的日子。每一份苦难，都让他更加珍惜眼前的美好。"
        },
        {
          "id": "s47",
          "text": "花园里的孩子和大人，都称赞他是湖上最美的天鹅。可他只是微微一笑，从不骄傲，依然那么温柔善良。"
        },
        {
          "id": "s48",
          "text": "这个故事告诉我们：不要因为别人长得不一样就嘲笑他；也不要因为自己暂时不如意而灰心。"
        },
        {
          "id": "s49",
          "text": "只要保持一颗善良的心，熬过最难的日子，每个人都会迎来属于自己的春天，绽放出自己最美的模样。"
        }
      ]
    }
  ],
  "category": "animal"
}
