{
  "id": "book_010",
  "title": "狼来了",
  "coverPath": "",
  "mode": "textOnly",
  "estimatedMinutes": 8,
  "pages": [
    {
      "id": "p1",
      "segments": [
        { "id": "s1", "text": "从前，在一个小山村里，住着一个放羊的孩子。他每天的工作，就是把羊群赶到村外的山坡上去吃草。" },
        { "id": "s2", "text": "山坡上的草又嫩又绿，羊儿们吃得开心极了，咩咩咩地叫个不停。可是放羊娃却觉得好无聊呀。" },
        { "id": "s3", "text": "他每天从早到晚都坐在山坡上，看着羊儿吃草，看着云朵飘过，一天又一天，连个说话的人都没有。" },
        { "id": "s4", "text": "山下村里的叔叔伯伯们，都忙着干活，没人愿意上山来陪他。放羊娃坐在草地上，叹了口气：“唉，天天这么坐着，真是没意思啊。”" }
      ]
    },
    {
      "id": "p2",
      "segments": [
        { "id": "s5", "text": "一天，放羊娃望着山下忙碌的村民，心里突然冒出一个坏念头：“我来逗逗他们，看看他们急成什么样！”" },
        { "id": "s6", "text": "他双手拢在嘴边，朝着山下大声喊起来：“狼来啦！狼来啦！救命啊！狼要吃羊啦！”" },
        { "id": "s7", "text": "山下的村民听见喊声，赶忙放下手里的活，扛着锄头、铁锹，呼哧呼哧地往山上跑。“快呀，狼来了，去救孩子和羊！”" },
        { "id": "s8", "text": "大伙儿气喘吁吁地跑到山坡上一看——咦？羊儿们还在安安静静地吃草，哪儿有狼的影子？" },
        { "id": "s9", "text": "放羊娃笑得前仰后合：“哈哈哈，你们上当了！我逗你们玩呢，哪儿有狼呀，看把你们急的！”" },
        { "id": "s10", "text": "村民们又气又无奈，摇摇头说：“孩子，这种事可不能开玩笑！下次别再瞎喊了。”说完，他们擦着汗下山去了。" }
      ]
    },
    {
      "id": "p3",
      "segments": [
        { "id": "s11", "text": "放羊娃看着村民们下山的背影，觉得好玩极了，心想：“原来逗他们这么有趣，下次我还要再来一次！”" },
        { "id": "s12", "text": "过了几天，放羊娃又觉得无聊了。他又双手拢在嘴边，朝着山下大喊：“狼来啦！狼来啦！快来人啊，真的狼来啦！”" },
        { "id": "s13", "text": "村民们听见喊声，又赶忙放下手里的活，往山上跑。有的人心里嘀咕：“这孩子不会又骗人吧？”" },
        { "id": "s14", "text": "可万一是真的呢？羊和孩子的命要紧呀！大家还是气喘吁吁地跑上了山。" },
        { "id": "s15", "text": "到了山上一看，羊儿们依然在悠闲地吃草，狼的影子还是没有。放羊娃又笑得直打滚：“哈哈哈，又上当了，又上当了！你们太好骗啦！”" }
      ]
    },
    {
      "id": "p4",
      "segments": [
        { "id": "s16", "text": "村民们这回可真生气了。一位老伯伯气得胡子都翘起来，指着放羊娃说：“你这孩子，怎么能拿这种事开玩笑？" },
        { "id": "s17", "text": "我们辛辛苦苦干着活，跑上来救你，你却骗我们！你以后再喊狼来了，我们可再也不信你了！”" },
        { "id": "s18", "text": "其他村民也纷纷指责他：“就是，太不应该了！”“下次休想再骗我们！”大家愤愤地下了山，从此对放羊娃的话都不太相信了。" },
        { "id": "s19", "text": "放羊娃看着村民们生气的样子，挠挠头，心想：“哼，不就和你们开个玩笑嘛，至于这么生气吗？”他没把这事放在心上。" }
      ]
    },
    {
      "id": "p5",
      "segments": [
        { "id": "s20", "text": "又过了几天，太阳快下山了，放羊娃正准备赶着羊群回家。突然，他听见身后传来沙沙的声音。" },
        { "id": "s21", "text": "他猛地回头一看——哎呀，不得了！灌木丛后面，一只眼睛发着绿光的大灰狼，正张着血盆大口，悄悄地逼近羊群！" },
        { "id": "s22", "text": "羊儿们吓坏了，咩咩咩地乱叫着四处逃窜。放羊娃吓得脸都白了，腿也软了，跌跌撞撞地往山顶跑。" },
        { "id": "s23", "text": "“狼来啦！狼来啦！真的狼来啦！救命啊！快来救救我和羊啊！”放羊娃用尽全身力气，朝着山下大喊。" }
      ]
    },
    {
      "id": "p6",
      "segments": [
        { "id": "s24", "text": "山下的村民们听见了，可是大家你看看我，我看看你，谁也没动弹。" },
        { "id": "s25", "text": "“又来这套，我才不信呢！”一个村民说。“这小子，又想骗咱们上去，没门！”另一个村民说。" },
        { "id": "s26", "text": "“别理他，专心干活。”村民们议论纷纷，谁也没把他的话当回事。" },
        { "id": "s27", "text": "放羊娃在山上拼命地喊：“求求你们，狼真的来了！快来人啊！这次是真的！”" },
        { "id": "s28", "text": "可是山下的人只当他又在开玩笑，谁也没有上山。放羊娃喊得嗓子都哑了，眼睛都红了，可是一个人影也没看见。" }
      ]
    },
    {
      "id": "p7",
      "segments": [
        { "id": "s29", "text": "大灰狼凶猛地扑向羊群，一只、两只、三只……好多羊都被狼咬死了，有的还被叼走了。" },
        { "id": "s30", "text": "放羊娃躲在石头后面，又害怕又伤心，眼泪吧嗒吧嗒地掉下来。他眼睁睁看着自己心爱的羊一只只倒下，却一点办法也没有。" },
        { "id": "s31", "text": "直到天黑，大灰狼吃饱了，才大摇大摆地离开了山坡。放羊娃这才敢出来，看着一片狼藉的山坡，放声大哭。" },
        { "id": "s32", "text": "他跌跌撞撞地跑下山，扑到老伯伯怀里，哭得上气不接下气：“狼……狼真的来了……我喊了，可是没人来……呜呜呜……”" }
      ]
    },
    {
      "id": "p8",
      "segments": [
        { "id": "s33", "text": "村民们听了他的哭诉，又看到山坡上死伤的羊，这才相信他这次说的是真话。" },
        { "id": "s34", "text": "可是已经晚了，损失已经造成了。老伯伯叹了口气，拍拍放羊娃的肩膀，语重心长地说：" },
        { "id": "s35", "text": "“孩子，你看，撒谎的代价多大啊。你前两次骗大家，大家就不信任你了。等你说真话的时候，也没人愿意再相信你啦。”" },
        { "id": "s36", "text": "放羊娃后悔极了，低下头哇哇大哭：“我错了，我以后再也不撒谎了，再也不敢了……”" }
      ]
    },
    {
      "id": "p9",
      "segments": [
        { "id": "s37", "text": "从那以后，放羊娃再也不敢撒谎了。他每天老老实实地放羊，再也没骗过村民们。" },
        { "id": "s38", "text": "可是那些被狼咬死的羊，再也回不来了。这份沉痛的教训，他记了一辈子。" },
        { "id": "s39", "text": "村民们也慢慢重新相信了他。可是每当他想起那次经历，心里还是又痛又悔。" },
        { "id": "s40", "text": "这个故事告诉我们：诚实是做人的根本。一次撒谎，可能让你失去别人的信任；再想说真话的时候，已经没人愿意相信你了。" },
        { "id": "s41", "text": "所以呀，从小就要做一个诚实的孩子，永远不要拿重要的事情开玩笑。" }
      ]
    }
  ]
}
